detector/__init__.py
detector/dependency.py
detector/detect.py
detector/detect_docker.py
detector/detect_java.py
detector/detect_nodejs.py
detector/detect_python.py
dependency_detector-0.7.0.dist-info/LICENSE
dependency_detector-0.7.0.dist-info/METADATA
dependency_detector-0.7.0.dist-info/WHEEL
dependency_detector-0.7.0.dist-info/entry_points.txt
dependency_detector-0.7.0.dist-info/top_level.txt
dependency_detector-0.7.0.dist-info/RECORD
